cidrbrewer.py
setup.cfg
setup.py
cidr_brewer.egg-info/PKG-INFO
cidr_brewer.egg-info/SOURCES.txt
cidr_brewer.egg-info/dependency_links.txt
cidr_brewer.egg-info/entry_points.txt
cidr_brewer.egg-info/top_level.txt