Metadata-Version: 1.0
Name: cidr-brewer
Version: 1.0.0
Summary: A CLI utility for working with classless IP addresses
Home-page: https://github.com/caleb531/cidr-brewer
Author: Caleb Evans
Author-email: caleb@calebevans.me
License: MIT
Keywords: networking ip addresses cidr
Platform: UNKNOWN
